{"data":{"repository":{"object":{"blame":{"ranges":[{"startingLine":1,"endingLine":20,"age":10,"commit":{"history":{"edges":[{"node":{"message":"Taken a copy of latest code from 2.1.2-wso2v4","url":"https://github.com/wso2/wso2-synapse/commit/4c3c4446b40ce7055d7214405391f57b0f3a07cb"}},{"node":{"message":"Added README file for Synapse repository","url":"https://github.com/wso2/wso2-synapse/commit/d734114c9d9c548b88032dd373be6683c77bc7d6"}}]},"author":{"name":"vanjikumaran","email":"vanjikumaran@gmail.com"}}},{"startingLine":21,"endingLine":22,"age":6,"commit":{"history":{"edges":[{"node":{"message":"introducing Synapse Handlers","url":"https://github.com/wso2/wso2-synapse/commit/7f37117a7e13df0398ca28127edacbabb048bd56"}},{"node":{"message":"make call non blocking return statement more clear","url":"https://github.com/wso2/wso2-synapse/commit/8773b335e9ddd3e02ce3c454d14b925e5d0f9640"}}]},"author":{"name":"Isuru U","email":"isuruu@Isurus-MacBook-Pro.local"}}},{"startingLine":23,"endingLine":26,"age":10,"commit":{"history":{"edges":[{"node":{"message":"Taken a copy of latest code from 2.1.2-wso2v4","url":"https://github.com/wso2/wso2-synapse/commit/4c3c4446b40ce7055d7214405391f57b0f3a07cb"}},{"node":{"message":"Added README file for Synapse repository","url":"https://github.com/wso2/wso2-synapse/commit/d734114c9d9c548b88032dd373be6683c77bc7d6"}}]},"author":{"name":"vanjikumaran","email":"vanjikumaran@gmail.com"}}},{"startingLine":27,"endingLine":27,"age":6,"commit":{"history":{"edges":[{"node":{"message":"introducing Synapse Handlers","url":"https://github.com/wso2/wso2-synapse/commit/7f37117a7e13df0398ca28127edacbabb048bd56"}},{"node":{"message":"make call non blocking return statement more clear","url":"https://github.com/wso2/wso2-synapse/commit/8773b335e9ddd3e02ce3c454d14b925e5d0f9640"}}]},"author":{"name":"Isuru U","email":"isuruu@Isurus-MacBook-Pro.local"}}},{"startingLine":28,"endingLine":177,"age":10,"commit":{"history":{"edges":[{"node":{"message":"Taken a copy of latest code from 2.1.2-wso2v4","url":"https://github.com/wso2/wso2-synapse/commit/4c3c4446b40ce7055d7214405391f57b0f3a07cb"}},{"node":{"message":"Added README file for Synapse repository","url":"https://github.com/wso2/wso2-synapse/commit/d734114c9d9c548b88032dd373be6683c77bc7d6"}}]},"author":{"name":"vanjikumaran","email":"vanjikumaran@gmail.com"}}},{"startingLine":178,"endingLine":178,"age":6,"commit":{"history":{"edges":[{"node":{"message":"introducing Synapse Handlers","url":"https://github.com/wso2/wso2-synapse/commit/7f37117a7e13df0398ca28127edacbabb048bd56"}},{"node":{"message":"make call non blocking return statement more clear","url":"https://github.com/wso2/wso2-synapse/commit/8773b335e9ddd3e02ce3c454d14b925e5d0f9640"}}]},"author":{"name":"Isuru U","email":"isuruu@Isurus-MacBook-Pro.local"}}},{"startingLine":179,"endingLine":186,"age":1,"commit":{"history":{"edges":[{"node":{"message":"ESBJAVA-3770 Message size based filtering to prevent OOM. (#679)\n\n* adding fix for ESBJAVA-3770","url":"https://github.com/wso2/wso2-synapse/commit/1aff92c4bad968f78cf38577cbb7c01516475217"}},{"node":{"message":"Merge pull request #681 from nuwanw/master\n\nfixing the issue ESBJAVA-4966","url":"https://github.com/wso2/wso2-synapse/commit/8cada804710fb2c29404155f85a27e1b1d061e66"}}]},"author":{"name":"Kevin Ratnasekera","email":"djkevincr@yahoo.com"}}},{"startingLine":187,"endingLine":189,"age":10,"commit":{"history":{"edges":[{"node":{"message":"Taken a copy of latest code from 2.1.2-wso2v4","url":"https://github.com/wso2/wso2-synapse/commit/4c3c4446b40ce7055d7214405391f57b0f3a07cb"}},{"node":{"message":"Added README file for Synapse repository","url":"https://github.com/wso2/wso2-synapse/commit/d734114c9d9c548b88032dd373be6683c77bc7d6"}}]},"author":{"name":"vanjikumaran","email":"vanjikumaran@gmail.com"}}},{"startingLine":190,"endingLine":257,"age":6,"commit":{"history":{"edges":[{"node":{"message":"introducing Synapse Handlers","url":"https://github.com/wso2/wso2-synapse/commit/7f37117a7e13df0398ca28127edacbabb048bd56"}},{"node":{"message":"make call non blocking return statement more clear","url":"https://github.com/wso2/wso2-synapse/commit/8773b335e9ddd3e02ce3c454d14b925e5d0f9640"}}]},"author":{"name":"Isuru U","email":"isuruu@Isurus-MacBook-Pro.local"}}},{"startingLine":258,"endingLine":328,"age":10,"commit":{"history":{"edges":[{"node":{"message":"Taken a copy of latest code from 2.1.2-wso2v4","url":"https://github.com/wso2/wso2-synapse/commit/4c3c4446b40ce7055d7214405391f57b0f3a07cb"}},{"node":{"message":"Added README file for Synapse repository","url":"https://github.com/wso2/wso2-synapse/commit/d734114c9d9c548b88032dd373be6683c77bc7d6"}}]},"author":{"name":"vanjikumaran","email":"vanjikumaran@gmail.com"}}},{"startingLine":329,"endingLine":340,"age":6,"commit":{"history":{"edges":[{"node":{"message":"introducing Synapse Handlers","url":"https://github.com/wso2/wso2-synapse/commit/7f37117a7e13df0398ca28127edacbabb048bd56"}},{"node":{"message":"make call non blocking return statement more clear","url":"https://github.com/wso2/wso2-synapse/commit/8773b335e9ddd3e02ce3c454d14b925e5d0f9640"}}]},"author":{"name":"Isuru U","email":"isuruu@Isurus-MacBook-Pro.local"}}},{"startingLine":341,"endingLine":341,"age":10,"commit":{"history":{"edges":[{"node":{"message":"Taken a copy of latest code from 2.1.2-wso2v4","url":"https://github.com/wso2/wso2-synapse/commit/4c3c4446b40ce7055d7214405391f57b0f3a07cb"}},{"node":{"message":"Added README file for Synapse repository","url":"https://github.com/wso2/wso2-synapse/commit/d734114c9d9c548b88032dd373be6683c77bc7d6"}}]},"author":{"name":"vanjikumaran","email":"vanjikumaran@gmail.com"}}}]}}}}}